[
  {
    "name": "Growth Equity Fund",
    "type": "Equity",
    "return": "12%",
    "assetClass": "Equity",
    "description": "Focused on long-term capital appreciation by investing in high-growth companies.",
    "riskLevel": "High",
    "liquidity": "Low",
    "pros": "High returns, growth potential",
    "cons": "High risk, market volatility"
  },
  {
    "name": "Fixed Income Secure Plan",
    "type": "Fixed Income",
    "return": "6.5%",
    "assetClass": "Fixed Income",
    "description": "Provides regular interest payments in the form of stable returns by investing in government and corporate bonds.",
    "riskLevel": "Low",
    "liquidity": "Medium",
    "pros": "Stable returns, lower risk",
    "cons": "Lower returns, inflation risk"
  },
  {
    "name": "Real Estate Investment Trust",
    "type": "Real Estate",
    "return": "8%",
    "assetClass": "Real Estate",
    "description": "Invests in commercial and residential real estate projects across urban areas.",
    "riskLevel": "Medium",
    "liquidity": "Low",
    "pros": "Tangible assets, passive income",
    "cons": "Illiquid, market sensitivity"
  },
  {
    "name": "Gold & Commodities Basket",
    "type": "Commodities",
    "return": "7%",
    "assetClass": "Commodities",
    "description": "Diversified commodity exposure including gold, oil, and metals for hedging inflation.",
    "riskLevel": "Medium", 
    "liquidity": "High",
    "pros": "Inflation hedge, diversification",
    "cons": "Price volatility, no income"
  },
  {
    "name": "Ultra-Liquid Fund",
    "type": "Cash & Cash Equivalents",
    "return": "4%",
    "assetClass": "Cash and Cash Equivalence",
    "description": "Designed for short-term liquidity needs with low risk and easy access.",
    "riskLevel": "Low",
    "liquidity": "Very High",
    "pros": "Very low risk, high liquidity",
    "cons": "Minimal returns, not growth-oriented"
  },
  {
    "name": "Growth Equity Fund",
    "type": "Equity",
    "return": "12%",
    "assetClass": "Equity",
    "description": "Focused on long-term capital appreciation by investing in high-growth companies.",
    "riskLevel": "High",
    "liquidity": "Low",
    "pros": "High returns, growth potential",
    "cons": "High risk, market volatility"
  },
  {
    "name": "Fixed Income Secure Plan",
    "type": "Fixed Income",
    "return": "6.5%",
    "assetClass": "Fixed Income",
    "description": "Provides regular interest payments in the form of stable returns by investing in government and corporate bonds.",
    "riskLevel": "Low",
    "liquidity": "Medium",
    "pros": "Stable returns, lower risk",
    "cons": "Lower returns, inflation risk"
  },
  {
    "name": "Real Estate Investment Trust",
    "type": "Real Estate",
    "return": "8%",
    "assetClass": "Real Estate",
    "description": "Invests in commercial and residential real estate projects across urban areas.",
    "riskLevel": "Medium",
    "liquidity": "Low",
    "pros": "Tangible assets, passive income",
    "cons": "Illiquid, market sensitivity"
  },
  {
    "name": "Gold & Commodities Basket",
    "type": "Commodities",
    "return": "7%",
    "assetClass": "Commodities",
    "description": "Diversified commodity exposure including gold, oil, and metals for hedging inflation.",
    "riskLevel": "Medium",
    "liquidity": "High",
    "pros": "Inflation hedge, diversification",
    "cons": "Price volatility, no income"
  },
  {
    "name": "Ultra-Liquid Fund",
    "type": "Cash & Cash Equivalents",
    "return": "4%",
    "assetClass": "Cash and Cash Equivalence",
    "description": "Designed for short-term liquidity needs with low risk and easy access.",
    "riskLevel": "Low",
    "liquidity": "Very High",
    "pros": "Very low risk, high liquidity",
    "cons": "Minimal returns, not growth-oriented"
  },
  {
    "name": "Growth Equity Fund",
    "type": "Equity",
    "return": "12%",
    "assetClass": "Equity",
    "description": "Focused on long-term capital appreciation by investing in high-growth companies.",
    "riskLevel": "High",
    "liquidity": "Low",
    "pros": "High returns, growth potential",
    "cons": "High risk, market volatility"
  },
  {
    "name": "Fixed Income Secure Plan",
    "type": "Fixed Income",
    "return": "6.5%",
    "assetClass": "Fixed Income",
    "description": "Provides regular interest payments in the form of stable returns by investing in government and corporate bonds.",
    "riskLevel": "Low",
    "liquidity": "Medium",
    "pros": "Stable returns, lower risk",
    "cons": "Lower returns, inflation risk"
  },
  {
    "name": "Real Estate Investment Trust",
    "type": "Real Estate",
    "return": "8%",
    "assetClass": "Real Estate",
    "description": "Invests in commercial and residential real estate projects across urban areas.",
    "riskLevel": "Medium",
    "liquidity": "Low",
    "pros": "Tangible assets, passive income",
    "cons": "Illiquid, market sensitivity"
  },
  {
    "name": "Gold & Commodities Basket",
    "type": "Commodities",
    "return": "7%",
    "assetClass": "Commodities",
    "description": "Diversified commodity exposure including gold, oil, and metals for hedging inflation.",
    "riskLevel": "Medium",
    "liquidity": "High",
    "pros": "Inflation hedge, diversification",
    "cons": "Price volatility, no income"
  },
  {
    "name": "Ultra-Liquid Fund",
    "type": "Cash & Cash Equivalents",
    "return": "4%",
    "assetClass": "Cash and Cash Equivalence",
    "description": "Designed for short-term liquidity needs with low risk and easy access.",
    "riskLevel": "Low",
    "liquidity": "Very High",
    "pros": "Very low risk, high liquidity",
    "cons": "Minimal returns, not growth-oriented"
  },
  {
    "name": "Growth Equity Fund",
    "type": "Equity",
    "return": "12%",
    "assetClass": "Equity",
    "description": "Focused on long-term capital appreciation by investing in high-growth companies.",
    "riskLevel": "High",
    "liquidity": "Low",
    "pros": "High returns, growth potential",
    "cons": "High risk, market volatility"
  },
  {
    "name": "Fixed Income Secure Plan",
    "type": "Fixed Income",
    "return": "6.5%",
    "assetClass": "Fixed Income",
    "description": "Provides regular interest payments in the form of stable returns by investing in government and corporate bonds.",
    "riskLevel": "Low",
    "liquidity": "Medium",
    "pros": "Stable returns, lower risk",
    "cons": "Lower returns, inflation risk"
  },
  {
    "name": "Real Estate Investment Trust",
    "type": "Real Estate",
    "return": "8%",
    "assetClass": "Real Estate",
    "description": "Invests in commercial and residential real estate projects across urban areas.",
    "riskLevel": "Medium",
    "liquidity": "Low",
    "pros": "Tangible assets, passive income",
    "cons": "Illiquid, market sensitivity"
  },
  {
    "name": "Gold & Commodities Basket",
    "type": "Commodities",
    "return": "7%",
    "assetClass": "Commodities",
    "description": "Diversified commodity exposure including gold, oil, and metals for hedging inflation.",
    "riskLevel": "Medium",
    "liquidity": "High",
    "pros": "Inflation hedge, diversification",
    "cons": "Price volatility, no income"
  },
  {
    "name": "Ultra-Liquid Fund",
    "type": "Cash & Cash Equivalents",
    "return": "4%",
    "assetClass": "Cash and Cash Equivalence",
    "description": "Designed for short-term liquidity needs with low risk and easy access.",
    "riskLevel": "Low",
    "liquidity": "Very High",
    "pros": "Very low risk, high liquidity",
    "cons": "Minimal returns, not growth-oriented"
  },
  {
    "name": "Growth Equity Fund",
    "type": "Equity",
    "return": "12%",
    "assetClass": "Equity",
    "description": "Focused on long-term capital appreciation by investing in high-growth companies.",
    "riskLevel": "High",
    "liquidity": "Low",
    "pros": "High returns, growth potential",
    "cons": "High risk, market volatility"
  },
  {
    "name": "Fixed Income Secure Plan",
    "type": "Fixed Income",
    "return": "6.5%",
    "assetClass": "Fixed Income",
    "description": "Provides regular interest payments in the form of stable returns by investing in government and corporate bonds.",
    "riskLevel": "Low",
    "liquidity": "Medium",
    "pros": "Stable returns, lower risk",
    "cons": "Lower returns, inflation risk"
  },
  {
    "name": "Real Estate Investment Trust",
    "type": "Real Estate",
    "return": "8%",
    "assetClass": "Real Estate",
    "description": "Invests in commercial and residential real estate projects across urban areas.",
    "riskLevel": "Medium",
    "liquidity": "Low",
    "pros": "Tangible assets, passive income",
    "cons": "Illiquid, market sensitivity"
  },
  {
    "name": "Gold & Commodities Basket",
    "type": "Commodities",
    "return": "7%",
    "assetClass": "Commodities",
    "description": "Diversified commodity exposure including gold, oil, and metals for hedging inflation.",
    "riskLevel": "Medium",
    "liquidity": "High",
    "pros": "Inflation hedge, diversification",
    "cons": "Price volatility, no income"
  },
  {
    "name": "Ultra-Liquid Fund",
    "type": "Cash & Cash Equivalents",
    "return": "4%",
    "assetClass": "Cash and Cash Equivalence",
    "description": "Designed for short-term liquidity needs with low risk and easy access.",
    "riskLevel": "Low",
    "liquidity": "Very High",
    "pros": "Very low risk, high liquidity",
    "cons": "Minimal returns, not growth-oriented"
  },
  {
    "name": "Growth Equity Fund",
    "type": "Equity",
    "return": "12%",
    "assetClass": "Equity",
    "description": "Focused on long-term capital appreciation by investing in high-growth companies.",
    "riskLevel": "High",
    "liquidity": "Low",
    "pros": "High returns, growth potential",
    "cons": "High risk, market volatility"
  },
  {
    "name": "Fixed Income Secure Plan",
    "type": "Fixed Income",
    "return": "6.5%",
    "assetClass": "Fixed Income",
    "description": "Provides regular interest payments in the form of stable returns by investing in government and corporate bonds.",
    "riskLevel": "Low",
    "liquidity": "Medium",
    "pros": "Stable returns, lower risk",
    "cons": "Lower returns, inflation risk"
  },
  {
    "name": "Real Estate Investment Trust",
    "type": "Real Estate",
    "return": "8%",
    "assetClass": "Real Estate",
    "description": "Invests in commercial and residential real estate projects across urban areas.",
    "riskLevel": "Medium",
    "liquidity": "Low",
    "pros": "Tangible assets, passive income",
    "cons": "Illiquid, market sensitivity"
  },
  {
    "name": "Gold & Commodities Basket",
    "type": "Commodities",
    "return": "7%",
    "assetClass": "Commodities",
    "description": "Diversified commodity exposure including gold, oil, and metals for hedging inflation.",
    "riskLevel": "Medium",
    "liquidity": "High",
    "pros": "Inflation hedge, diversification",
    "cons": "Price volatility, no income"
  },
  {
    "name": "Ultra-Liquid Fund",
    "type": "Cash & Cash Equivalents",
    "return": "4%",
    "assetClass": "Cash and Cash Equivalence",
    "description": "Designed for short-term liquidity needs with low risk and easy access.",
    "riskLevel": "Low",
    "liquidity": "Very High",
    "pros": "Very low risk, high liquidity",
    "cons": "Minimal returns, not growth-oriented"
  },
  {
    "name": "Growth Equity Fund",
    "type": "Equity",
    "return": "12%",
    "assetClass": "Equity",
    "description": "Focused on long-term capital appreciation by investing in high-growth companies.",
    "riskLevel": "High",
    "liquidity": "Low",
    "pros": "High returns, growth potential",
    "cons": "High risk, market volatility"
  },
  {
    "name": "Fixed Income Secure Plan",
    "type": "Fixed Income",
    "return": "6.5%",
    "assetClass": "Fixed Income",
    "description": "Provides regular interest payments in the form of stable returns by investing in government and corporate bonds.",
    "riskLevel": "Low",
    "liquidity": "Medium",
    "pros": "Stable returns, lower risk",
    "cons": "Lower returns, inflation risk"
  },
  {
    "name": "Real Estate Investment Trust",
    "type": "Real Estate",
    "return": "8%",
    "assetClass": "Real Estate",
    "description": "Invests in commercial and residential real estate projects across urban areas.",
    "riskLevel": "Medium",
    "liquidity": "Low",
    "pros": "Tangible assets, passive income",
    "cons": "Illiquid, market sensitivity"
  },
  {
    "name": "Gold & Commodities Basket",
    "type": "Commodities",
    "return": "7%",
    "assetClass": "Commodities",
    "description": "Diversified commodity exposure including gold, oil, and metals for hedging inflation.",
    "riskLevel": "Medium",
    "liquidity": "High",
    "pros": "Inflation hedge, diversification",
    "cons": "Price volatility, no income"
  },
  {
    "name": "Ultra-Liquid Fund",
    "type": "Cash & Cash Equivalents",
    "return": "4%",
    "assetClass": "Cash and Cash Equivalence",
    "description": "Designed for short-term liquidity needs with low risk and easy access.",
    "riskLevel": "Low",
    "liquidity": "Very High",
    "pros": "Very low risk, high liquidity",
    "cons": "Minimal returns, not growth-oriented"
  },
  {
    "name": "Growth Equity Fund",
    "type": "Equity",
    "return": "12%",
    "assetClass": "Equity",
    "description": "Focused on long-term capital appreciation by investing in high-growth companies.",
    "riskLevel": "High",
    "liquidity": "Low",
    "pros": "High returns, growth potential",
    "cons": "High risk, market volatility"
  },
  {
    "name": "Fixed Income Secure Plan",
    "type": "Fixed Income",
    "return": "6.5%",
    "assetClass": "Fixed Income",
    "description": "Provides regular interest payments in the form of stable returns by investing in government and corporate bonds.",
    "riskLevel": "Low",
    "liquidity": "Medium",
    "pros": "Stable returns, lower risk",
    "cons": "Lower returns, inflation risk"
  },
  {
    "name": "Real Estate Investment Trust",
    "type": "Real Estate",
    "return": "8%",
    "assetClass": "Real Estate",
    "description": "Invests in commercial and residential real estate projects across urban areas.",
    "riskLevel": "Medium",
    "liquidity": "Low",
    "pros": "Tangible assets, passive income",
    "cons": "Illiquid, market sensitivity"
  },
  {
    "name": "Gold & Commodities Basket",
    "type": "Commodities",
    "return": "7%",
    "assetClass": "Commodities",
    "description": "Diversified commodity exposure including gold, oil, and metals for hedging inflation.",
    "riskLevel": "Medium",
    "liquidity": "High",
    "pros": "Inflation hedge, diversification",
    "cons": "Price volatility, no income"
  },
  {
    "name": "Ultra-Liquid Fund",
    "type": "Cash & Cash Equivalents",
    "return": "4%",
    "assetClass": "Cash and Cash Equivalence",
    "description": "Designed for short-term liquidity needs with low risk and easy access.",
    "riskLevel": "Low",
    "liquidity": "Very High",
    "pros": "Very low risk, high liquidity",
    "cons": "Minimal returns, not growth-oriented"
  },
  {
    "name": "Growth Equity Fund",
    "type": "Equity",
    "return": "12%",
    "assetClass": "Equity",
    "description": "Focused on long-term capital appreciation by investing in high-growth companies.",
    "riskLevel": "High",
    "liquidity": "Low",
    "pros": "High returns, growth potential",
    "cons": "High risk, market volatility"
  },
  {
    "name": "Fixed Income Secure Plan",
    "type": "Fixed Income",
    "return": "6.5%",
    "assetClass": "Fixed Income",
    "description": "Provides regular interest payments in the form of stable returns by investing in government and corporate bonds.",
    "riskLevel": "Low",
    "liquidity": "Medium",
    "pros": "Stable returns, lower risk",
    "cons": "Lower returns, inflation risk"
  },
  {
    "name": "Real Estate Investment Trust",
    "type": "Real Estate",
    "return": "8%",
    "assetClass": "Real Estate",
    "description": "Invests in commercial and residential real estate projects across urban areas.",
    "riskLevel": "Medium",
    "liquidity": "Low",
    "pros": "Tangible assets, passive income",
    "cons": "Illiquid, market sensitivity"
  },
  {
    "name": "Gold & Commodities Basket",
    "type": "Commodities",
    "return": "7%",
    "assetClass": "Commodities",
    "description": "Diversified commodity exposure including gold, oil, and metals for hedging inflation.",
    "riskLevel": "Medium",
    "liquidity": "High",
    "pros": "Inflation hedge, diversification",
    "cons": "Price volatility, no income"
  },
  {
    "name": "Ultra-Liquid Fund",
    "type": "Cash & Cash Equivalents",
    "return": "4%",
    "assetClass": "Cash and Cash Equivalence",
    "description": "Designed for short-term liquidity needs with low risk and easy access.",
    "riskLevel": "Low",
    "liquidity": "Very High",
    "pros": "Very low risk, high liquidity",
    "cons": "Minimal returns, not growth-oriented"
  },
  {
    "name": "Growth Equity Fund",
    "type": "Equity",
    "return": "12%",
    "assetClass": "Equity",
    "description": "Focused on long-term capital appreciation by investing in high-growth companies.",
    "riskLevel": "High",
    "liquidity": "Low",
    "pros": "High returns, growth potential",
    "cons": "High risk, market volatility"
  },
  {
    "name": "Fixed Income Secure Plan",
    "type": "Fixed Income",
    "return": "6.5%",
    "assetClass": "Fixed Income",
    "description": "Provides regular interest payments in the form of stable returns by investing in government and corporate bonds.",
    "riskLevel": "Low",
    "liquidity": "Medium",
    "pros": "Stable returns, lower risk",
    "cons": "Lower returns, inflation risk"
  },
  {
    "name": "Real Estate Investment Trust",
    "type": "Real Estate",
    "return": "8%",
    "assetClass": "Real Estate",
    "description": "Invests in commercial and residential real estate projects across urban areas.",
    "riskLevel": "Medium",
    "liquidity": "Low",
    "pros": "Tangible assets, passive income",
    "cons": "Illiquid, market sensitivity"
  },
  {
    "name": "Gold & Commodities Basket",
    "type": "Commodities",
    "return": "7%",
    "assetClass": "Commodities",
    "description": "Diversified commodity exposure including gold, oil, and metals for hedging inflation.",
    "riskLevel": "Medium",
    "liquidity": "High",
    "pros": "Inflation hedge, diversification",
    "cons": "Price volatility, no income"
  },
  {
    "name": "Ultra-Liquid Fund",
    "type": "Cash & Cash Equivalents",
    "return": "4%",
    "assetClass": "Cash and Cash Equivalence",
    "description": "Designed for short-term liquidity needs with low risk and easy access.",
    "riskLevel": "Low",
    "liquidity": "Very High",
    "pros": "Very low risk, high liquidity",
    "cons": "Minimal returns, not growth-oriented"
  }
]